fourcipp/__init__.py
fourcipp/fourc_input.py
fourcipp/version.py
fourcipp/config/4C_metadata.yaml
fourcipp/config/4C_schema.json
fourcipp/config/config.yaml
fourcipp/legacy_io/__init__.py
fourcipp/legacy_io/element.py
fourcipp/legacy_io/inline_dat.py
fourcipp/legacy_io/node.py
fourcipp/legacy_io/node_topology.py
fourcipp/legacy_io/particle.py
fourcipp/utils/__init__.py
fourcipp/utils/cli.py
fourcipp/utils/configuration.py
fourcipp/utils/converter.py
fourcipp/utils/dict_utils.py
fourcipp/utils/metadata.py
fourcipp/utils/not_set.py
fourcipp/utils/type_hinting.py
fourcipp/utils/validation.py
fourcipp/utils/yaml_io.py
fourcipp-1.49.0.dist-info/licenses/LICENSE
fourcipp-1.49.0.dist-info/METADATA
fourcipp-1.49.0.dist-info/WHEEL
fourcipp-1.49.0.dist-info/entry_points.txt
fourcipp-1.49.0.dist-info/top_level.txt
fourcipp-1.49.0.dist-info/RECORD
