Metadata-Version: 2.4
Name: FourCIPP
Version: 1.49.0
Summary: A streamlined Python Parser for 4C input files
Author: FourCIPP Authors
License: The MIT License (MIT)
Project-URL: Repository, https://github.com/4C-multiphysics/fourcipp/
Project-URL: Issues, https://github.com/4C-multiphysics/fourcipp/issues/
Requires-Python: >=3.10
License-File: LICENSE
Requires-Dist: jsonschema-rs
Requires-Dist: loguru
Requires-Dist: numpy
Requires-Dist: rapidyaml
Requires-Dist: regex
Provides-Extra: dev
Requires-Dist: pre-commit; extra == "dev"
Requires-Dist: pytest; extra == "dev"
Requires-Dist: pytest-cov; extra == "dev"
Requires-Dist: pip-tools; extra == "dev"
Requires-Dist: pytest-xdist; extra == "dev"
Dynamic: license-file
